wsuks/__init__.py
wsuks/executables/Enable-LocalAccountTokenFilterPolicy.ps1
wsuks/executables/PsExec.exe
wsuks/executables/PsExec64.exe
wsuks/lib/__init__.py
wsuks/lib/argparser.py
wsuks/lib/arpspoofer.py
wsuks/lib/logger.py
wsuks/lib/regpol_parser.py
wsuks/lib/router.py
wsuks/lib/sysvolparser.py
wsuks/lib/wsusserver.py
wsuks/wsuks.py
wsuks/xml_files/get-authorization-cookie.xml
wsuks/xml_files/get-config.xml
wsuks/xml_files/get-cookie.xml
wsuks/xml_files/get-extended-update-info.xml
wsuks/xml_files/internal-error.xml
wsuks/xml_files/register-computer.xml
wsuks/xml_files/report-event-batch.xml
wsuks/xml_files/sync-updates.xml
wsuks-1.1.0.dist-info/METADATA
wsuks-1.1.0.dist-info/WHEEL
wsuks-1.1.0.dist-info/entry_points.txt
wsuks-1.1.0.dist-info/licenses/LICENSE
wsuks-1.1.0.dist-info/RECORD
