Metadata-Version: 2.4
Name: wsuks
Version: 1.1.0
Summary: Automating the MITM attack on WSUS
License: MIT
License-File: LICENSE
Author: Alexander Neff
Author-email: alex99.neff@gmx.de
Requires-Python: >=3.9,<4.0
Classifier: License :: OSI Approved :: MIT License
Classifier: Programming Language :: Python :: 3
Classifier: Programming Language :: Python :: 3.9
Classifier: Programming Language :: Python :: 3.10
Classifier: Programming Language :: Python :: 3.11
Classifier: Programming Language :: Python :: 3.12
Classifier: Programming Language :: Python :: 3.13
Classifier: Programming Language :: Python :: 3.14
Requires-Dist: bs4 (>=0.0.2,<0.0.3)
Requires-Dist: impacket (>=0.12.0,<0.13.0)
Requires-Dist: lxml (>=5.3.1,<6.0.0)
Requires-Dist: netifaces (>=0.11.0,<0.12.0)
Requires-Dist: registrypol (>=1.0.0,<2.0.0)
Requires-Dist: scapy (>=2.6.1,<3.0.0)
Requires-Dist: termcolor (>=2.4.0,<3.0.0)
Project-URL: Homepage, https://github.com/NeffIsBack/wsuks
Project-URL: Repository, https://github.com/Pennyw0rth/NetExec
